<?xml version="1.0" encoding="utf-8"?>
<resources>
<!-- PRIMÄR FARBEN: -->
    <!-- ROT -->
    <color name="holo_red_light">#EF5350</color>

    <!-- INDIGO -->
    <color name="holo_blue_light">#EF5350</color>

    <!-- GRÜN -->
    <color name="holo_green_light">#EF5350</color>

    <!-- ORANGE -->
    <color name="holo_orange_light">#EF5350</color>

    <!-- HELL BLAU -->
    <color name="holo_blue_bright">#EF5350</color>

    <!-- LILA -->
    <color name="holo_purple">#EF5350</color>

    <!-- GRAU -->
    <color name="darker_gray">#EF5350</color>

</resources>