<?xml version="1.0" encoding="utf-8"?>
<resources>
    <!-- PRIMÄR FARBEN: -->
    <!-- ROT -->
    <color name="holo_red_light">#EF5350</color>

    <!-- INDIGO -->
    <color name="holo_blue_light">#5C6BC0</color>

    <!-- GRÜN -->
    <color name="holo_green_light">#66BB6A</color>

    <!-- ORANGE -->
    <color name="holo_orange_light">#FFA000</color>

    <!-- Grau -->
    <color name="holo_gray_light">#757575</color>

    <!-- AKZENT FARBEN: -->
    <!-- ROT AKZENT: INDIGO -->
    <color name="holo_red_dark">#5C6BC0</color>
    <!-- INDIGO AKZENT: PINK -->
    <color name="holo_blue_dark">#EC407A</color>
    <!-- GRÜN AKZENT: BLAU -->
    <color name="holo_green_dark">#42A5F5</color>
    <!-- Orange AKZENT: Indigo -->
    <color name="holo_orange_dark">#7E8ACD</color>
</resources>