<?xml version="1.0" encoding="utf-8"?>
<resources>
    <!-- Accent -->
    <color name="accent_material_light">#d37a7a</color>

    <color name="holo_red_light">@*android:color/accent_material_light</color>
    <color name="holo_blue_light">@*android:color/accent_material_light</color>
    <color name="holo_green_light">@*android:color/accent_material_light</color>
    <color name="holo_orange_light">@*android:color/accent_material_light</color>
    <color name="holo_purple">@*android:color/accent_material_light</color>
    <color name="holo_gray_light">@*android:color/accent_material_light</color>
</resources>